reqTools/HttpRequestProcessor.py
reqTools/__init__.py
reqTools/domain/RequestHeaders.py
reqTools/domain/__init__.py
reqTools/enum/ContentTypeEnum.py
reqTools/enum/DataFormatEnum.py
reqTools/enum/MethodEnum.py
reqTools/enum/__init__.py
test/DataFormatEnumTest.py
test/HttpRequestTest.py
test/TextFormatUtilTest.py
test/__init__.py
util/ChromeBrowser.py
util/ConfigUtil.py
util/DateUtil.py
util/ExcelUtil.py
util/FileUtil.py
util/RequestHeadersUtil.py
util/RequestProcessUtil.py
util/SqliteUtil.py
util/TextFormatUtil.py
util/__init__.py
requestTools-2.0.0.0.dist-info/LICENSE
requestTools-2.0.0.0.dist-info/METADATA
requestTools-2.0.0.0.dist-info/WHEEL
requestTools-2.0.0.0.dist-info/top_level.txt
requestTools-2.0.0.0.dist-info/RECORD
