Metadata-Version: 2.1
Name: requestTools
Version: 2.0.0.0
Summary: http request tools
Home-page: 
Author: trimNiu
Author-email: fahongsun168@sina.com
License: BSD License
Platform: all
Classifier: Intended Audience :: Developers
Classifier: Operating System :: OS Independent
Classifier: Natural Language :: Chinese (Simplified)
Classifier: Programming Language :: Python :: 3.8
Classifier: Topic :: Software Development :: Libraries
License-File: LICENSE
Requires-Dist: requests
